pycrofluidics/__init__.py
pycrofluidics/common.py
pycrofluidics/elvemux.py
pycrofluidics/elveob.py
pycrofluidics/post_install.py
pycrofluidics/protocols.py
pycrofluidics-0.2.1.dist-info/LICENSE
pycrofluidics-0.2.1.dist-info/METADATA
pycrofluidics-0.2.1.dist-info/WHEEL
pycrofluidics-0.2.1.dist-info/entry_points.txt
pycrofluidics-0.2.1.dist-info/RECORD
