Metadata-Version: 2.1
Name: pycrofluidics
Version: 0.2.1
Summary: Control Elveflow microfluidic components using (relatively) simple Python bindings
Home-page: https://github.com/WetenSchaap/pycrofluidics
Author: Piet J.M. Swinkels
Requires-Python: >=3.10,<4.0
Classifier: Programming Language :: Python :: 3
Classifier: Programming Language :: Python :: 3.10
Classifier: Programming Language :: Python :: 3.11
Classifier: Programming Language :: Python :: 3.12
Requires-Dist: numpy (>=1.26.4,<2.0.0)
Requires-Dist: pandas (>=2.2.1,<3.0.0)
Requires-Dist: platformdirs (>=4.2.0,<5.0.0)
Requires-Dist: ruamel-yaml (>=0.18.6,<0.19.0)
Project-URL: Repository, https://github.com/WetenSchaap/pycrofluidics
